Workbook

Sheet NFL Teams
A1: Team | B1: Siege (Regular Season, all-time) (Siege) | C1: Niederlagen (Regular Season, all-time) (Niederlagen) | D1: Unentschieden (all-time) (Remis) | E1: Siegquote (Regular Season, all-time) (%) | F1: Playoff-Siege (all-time) (Siege) | G1: Hall-of-Famers (Personen) | H1: In der heutigen Stadt seit (Jahr) | I1: Stadionkapazität (Plätze) | J1: Stadion-Baukosten (Mio. USD) | K1: Breitengrad Stadion (° Nord) | L1: Längengrad Stadion (° West) | M1: Einwohner Metropolregion (Mio.) | N1: Social-Media-Follower (Mio.) | O1: YouTube-Abonnenten (Tsd.) | P1: Betriebsgewinn Saison 2025 (Mio. USD) | Q1: Anmerkung
A2: Arizona Cardinals | B2: 596 | C2: 826 | D2: 41 | E2: 0.421 | F2: 7 | G2: 13 | H2: 1988 | I2: 63400 | J2: 455 | K2: 33.528 | L2: 112.263 | M2: 5.229 | N2: 2.321 | O2: 121 | P2: 119 | Q2: Ältestes durchgehend bestehendes Profi-Team: Chicago → St. Louis (1960) → Arizona (1988).
A3: Atlanta Falcons | B3: 406 | C3: 521 | D3: 6 | E3: 0.438 | F3: 10 | G3: 2 | H3: 1966 | I3: 71000 | J3: 1500 | K3: 33.755 | L3: 84.401 | M3: 6.482 | N3: 3.933 | O3: 233 | P3: 240
A4: Baltimore Ravens | B4: 276 | C4: 208 | D4: 1 | E4: 0.57 | F4: 18 | G4: 3 | H4: 1996 | I4: 71008 | J4: 220 | K4: 39.278 | L4: 76.623 | M4: 2.858 | N4: 4.553 | O4: 353 | P4: 77 | Q4: Offiziell Neugründung 1996 (Browns-Geschichte blieb in Cleveland).
A5: Buffalo Bills | B5: 498 | C5: 510 | D5: 8 | E5: 0.494 | F5: 22 | G5: 9 | H5: 1960 | I5: 60108 | J5: 2100 | K5: 42.774 | L5: 78.787 | M5: 1.156 | N5: 4.558 | O5: 258 | P5: 58 | Q5: Neues Highmark Stadium seit 2026 ($2,1 Mrd.) – kleinstes Stadion der Liga.
A6: Carolina Panthers | B6: 227 | C6: 273 | D6: 1 | E6: 0.454 | F6: 9 | G6: 2 | H6: 1995 | I6: 75037 | J6: 242 | K6: 35.226 | L6: 80.853 | M6: 2.939 | N6: 5.073 | O6: 173 | P6: 88
A7: Chicago Bears | B7: 809 | C7: 652 | D7: 42 | E7: 0.552 | F7: 18 | G7: 29 | H7: 1921 | I7: 62500 | J7: 632 | K7: 41.862 | L7: 87.617 | M7: 9.434 | N7: 4.504 | O7: 304 | P7: 73 | Q7: Seit 1921 in Chicago (1920 Decatur Staleys). Meiste Remis & Hall-of-Famers. Baukosten = Umbau 2003.
A8: Cincinnati Bengals | B8: 409 | C8: 490 | D8: 5 | E8: 0.455 | F8: 10 | G8: 2 | H8: 1968 | I8: 65515 | J8: 450 | K8: 39.095 | L8: 84.516 | M8: 2.313 | N8: 3.668 | O8: 168 | P8: 71
A9: Cleveland Browns | B9: 567 | C9: 560 | D9: 14 | E9: 0.503 | F9: 17 | G9: 16 | H9: 1946 | I9: 67895 | J9: 290 | K9: 41.506 | L9: 81.7 | M9: 2.166 | N9: 3.555 | O9: 355 | P9: 110 | Q9: Erste Saison 1946 (AAFC); 1996–98 pausiert.
A10: Dallas Cowboys | B10: 576 | C10: 432 | D10: 7 | E10: 0.571 | F10: 36 | G10: 21 | H10: 1960 | I10: 80000 | J10: 1300 | K10: 32.748 | L10: 97.093 | M10: 8.477 | N10: 9.711 | O10: 511 | P10: 677 | Q10: Höchster Gewinn der Liga ($677 Mio.).
A11: Denver Broncos | B11: 532 | C11: 475 | D11: 10 | E11: 0.528 | F11: 24 | G11: 9 | H11: 1960 | I11: 76125 | J11: 364 | K11: 39.744 | L11: 105.02 | M11: 3.092 | N11: 4.443 | O11: 243 | P11: 97
A12: Detroit Lions | B12: 615 | C12: 717 | D12: 34 | E12: 0.463 | F12: 9 | G12: 16 | H12: 1934 | I12: 65000 | J12: 430 | K12: 42.34 | L12: 83.046 | M12: 4.391 | N12: 4.129 | O12: 329 | P12: 53
A13: Green Bay Packers | B13: 819 | C13: 611 | D13: 39 | E13: 0.571 | F13: 37 | G13: 27 | H13: 1921 | I13: 81441 | J13: 0.96 | K13: 44.501 | L13: 88.062 | M13: 0.337 | N13: 5.535 | O13: 235 | P13: 73 | Q13: Lambeau Field kostete 1957 nur $960'000. Kleinste Metropolregion.
A14: Houston Texans | B14: 174 | C14: 214 | D14: 1 | E14: 0.449 | F14: 7 | G14: 1 | H14: 2002 | I14: 72220 | J14: 352 | K14: 29.685 | L14: 95.411 | M14: 7.905 | N14: 4.062 | O14: 162 | P14: 160 | Q14: Jüngstes Team (2002).
A15: Indianapolis Colts | B15: 572 | C15: 519 | D15: 8 | E15: 0.524 | F15: 23 | G15: 13 | H15: 1984 | I15: 67000 | J15: 720 | K15: 39.76 | L15: 86.164 | M15: 2.206 | N15: 2.3 | O15: 100 | P15: 81 | Q15: Bis 1983 Baltimore Colts.
A16: Jacksonville Jaguars | B16: 215 | C16: 286 | D16: 0 | E16: 0.429 | F16: 8 | G16: 1 | H16: 1995 | I16: 69132 | J16: 134 | K16: 30.324 | L16: 81.637 | M16: 1.786 | N16: 2.083 | O16: 136 | P16: 31 | Q16: Nie ein Remis.
A17: Kansas City Chiefs | B17: 553 | C17: 452 | D17: 12 | E17: 0.55 | F17: 26 | G17: 13 | H17: 1963 | I17: 73426 | J17: 43 | K17: 39.049 | L17: 94.484 | M17: 2.271 | N17: 8.48 | O17: 1480 | P17: 51 | Q17: 1960–62 Dallas Texans. Meiste YouTube-Abonnenten.
A18: Las Vegas Raiders | B18: 512 | C18: 494 | D18: 11 | E18: 0.509 | F18: 25 | G18: 18 | H18: 2020 | I18: 66000 | J18: 1900 | K18: 36.091 | L18: 115.184 | M18: 2.407 | N18: 4.535 | O18: 335 | P18: 191 | Q18: Oakland → LA → Oakland → Las Vegas (2020).
A19: Los Angeles Chargers | B19: 505 | C19: 501 | D19: 11 | E19: 0.502 | F19: 12 | G19: 11 | H19: 2017 | I19: 70000 | J19: 5500 | K19: 33.953 | L19: 118.339 | M19: 12.844 | N19: 2.747 | O19: 447 | P19: 57 | Q19: 1961–2016 San Diego. Teilen SoFi Stadium ($5,5 Mrd.) mit den Rams.
A20: Los Angeles Rams | B20: 636 | C20: 611 | D20: 21 | E20: 0.51 | F20: 29 | G20: 16 | H20: 2016 | I20: 70000 | J20: 5500 | K20: 33.953 | L20: 118.339 | M20: 12.844 | N20: 3.489 | O20: 389 | P20: 335 | Q20: Cleveland → LA → St. Louis → LA (2016).
A21: Miami Dolphins | B21: 511 | C21: 418 | D21: 4 | E21: 0.55 | F21: 20 | G21: 10 | H21: 1966 | I21: 65326 | J21: 115 | K21: 25.958 | L21: 80.239 | M21: 6.391 | N21: 3.383 | O21: 183 | P21: 198
A22: Minnesota Vikings | B22: 546 | C22: 446 | D22: 11 | E22: 0.55 | F22: 21 | G22: 14 | H22: 1961 | I22: 66655 | J22: 1100 | K22: 44.974 | L22: 93.258 | M22: 3.79 | N22: 3.611 | O22: 411 | P22: 25
A23: New England Patriots | B23: 559 | C23: 449 | D23: 9 | E23: 0.554 | F23: 40 | G23: 6 | H23: 1960 | I23: 66829 | J23: 325 | K23: 42.091 | L23: 71.264 | M23: 5.034 | N23: 10.101 | O23: 401 | P23: 186 | Q23: Meiste Playoff-Siege (40, gleichauf mit SF) & Social-Media-Follower.
A24: New Orleans Saints | B24: 423 | C24: 491 | D24: 5 | E24: 0.463 | F24: 10 | G24: 5 | H24: 1967 | I24: 73208 | J24: 134 | K24: 29.951 | L24: 90.081 | M24: 0.971 | N24: 3.96 | O24: 160 | P24: 165
A25: New York Giants | B25: 728 | C25: 676 | D25: 34 | E25: 0.518 | F25: 25 | G25: 21 | H25: 1925 | I25: 82500 | J25: 1600 | K25: 40.813 | L25: 74.074 | M25: 20.112 | N25: 4.997 | O25: 297 | P25: 181 | Q25: Teilen MetLife Stadium (New Jersey) mit den Jets.
A26: New York Jets | B26: 436 | C26: 573 | D26: 8 | E26: 0.433 | F26: 12 | G26: 8 | H26: 1960 | I26: 82500 | J26: 1600 | K26: 40.813 | L26: 74.074 | M26: 20.112 | N26: 2.573 | O26: 173 | P26: 216 | Q26: Teilen MetLife Stadium (New Jersey) mit den Giants.
A27: Philadelphia Eagles | B27: 649 | C27: 645 | D27: 27 | E27: 0.502 | F27: 29 | G27: 12 | H27: 1933 | I27: 69596 | J27: 518 | K27: 39.901 | L27: 75.168 | M27: 6.329 | N27: 9.517 | O27: 917 | P27: 154
A28: Pittsburgh Steelers | B28: 691 | C28: 592 | D28: 22 | E28: 0.538 | F28: 36 | G28: 26 | H28: 1933 | I28: 68984 | J28: 281 | K28: 40.447 | L28: 80.016 | M28: 2.422 | N28: 7.763 | O28: 363 | P28: 74
A29: San Francisco 49ers | B29: 642 | C29: 531 | D29: 16 | E29: 0.547 | F29: 40 | G29: 16 | H29: 1946 | I29: 68500 | J29: 1300 | K29: 37.403 | L29: 121.97 | M29: 4.63 | N29: 6.645 | O29: 445 | P29: 126 | Q29: Stadion in Santa Clara; Metro = San Francisco–Oakland.
A30: Seattle Seahawks | B30: 416 | C30: 376 | D30: 1 | E30: 0.525 | F30: 19 | G30: 5 | H30: 1976 | I30: 69000 | J30: 360 | K30: 47.595 | L30: 122.332 | M30: 4.162 | N30: 6.332 | O30: 332 | P30: 131 | Q30: Super-Bowl-LX-Sieger. Nördlichstes und westlichstes Stadion.
A31: Tampa Bay Buccaneers | B31: 326 | C31: 466 | D31: 1 | E31: 0.412 | F31: 12 | G31: 5 | H31: 1976 | I31: 65890 | J31: 194 | K31: 27.976 | L31: 82.503 | M31: 3.419 | N31: 3.271 | O31: 271 | P31: 95
A32: Tennessee Titans | B32: 482 | C32: 529 | D32: 6 | E32: 0.477 | F32: 17 | G32: 7 | H32: 1997 | I32: 69143 | J32: 290 | K32: 36.166 | L32: 86.771 | M32: 2.197 | N32: 2.086 | O32: 85.6 | P32: 85 | Q32: Bis 1996 Houston Oilers; neues Stadion ab 2027.
A33: Washington Commanders | B33: 646 | C33: 660 | D33: 29 | E33: 0.495 | F33: 25 | G33: 17 | H33: 1937 | I33: 64000 | J33: 250 | K33: 38.908 | L33: 76.864 | M33: 6.466 | N33: 3.017 | O33: 317 | P33: 121 | Q33: 1932–36 Boston.

Sheet Ränge
A1: Team | B1: Siege (Regular Season, all-time) | C1: Niederlagen (Regular Season, all-time) | D1: Unentschieden (all-time) | E1: Siegquote (Regular Season, all-time) | F1: Playoff-Siege (all-time) | G1: Hall-of-Famers | H1: In der heutigen Stadt seit | I1: Stadionkapazität | J1: Stadion-Baukosten | K1: Breitengrad Stadion | L1: Längengrad Stadion | M1: Einwohner Metropolregion | N1: Social-Media-Follower | O1: YouTube-Abonnenten | P1: Betriebsgewinn Saison 2025
A2: ='NFL Teams'!A2 -> Arizona Cardinals | B2: =IF('NFL Teams'!B2="","",RANK('NFL Teams'!B2,'NFL Teams'!$B$2:$B$33,0)) -> 10 | C2: =IF('NFL Teams'!C2="","",RANK('NFL Teams'!C2,'NFL Teams'!$C$2:$C$33,0)) -> 1 | D2: =IF('NFL Teams'!D2="","",RANK('NFL Teams'!D2,'NFL Teams'!$D$2:$D$33,0)) -> 2 | E2: =IF('NFL Teams'!E2="","",RANK('NFL Teams'!E2,'NFL Teams'!$E$2:$E$33,0)) -> 31 | F2: =IF('NFL Teams'!F2="","",RANK('NFL Teams'!F2,'NFL Teams'!$F$2:$F$33,0)) -> 31 | G2: =IF('NFL Teams'!G2="","",RANK('NFL Teams'!G2,'NFL Teams'!$G$2:$G$33,0)) -> 13 | H2: =IF('NFL Teams'!H2="","",RANK('NFL Teams'!H2,'NFL Teams'!$H$2:$H$33,1)) -> 24 | I2: =IF('NFL Teams'!I2="","",RANK('NFL Teams'!I2,'NFL Teams'!$I$2:$I$33,0)) -> 30 | J2: =IF('NFL Teams'!J2="","",RANK('NFL Teams'!J2,'NFL Teams'!$J$2:$J$33,0)) -> 14 | K2: =IF('NFL Teams'!K2="","",RANK('NFL Teams'!K2,'NFL Teams'!$K$2:$K$33,0)) -> 26 | L2: =IF('NFL Teams'!L2="","",RANK('NFL Teams'!L2,'NFL Teams'!$L$2:$L$33,0)) -> 6 | M2: =IF('NFL Teams'!M2="","",RANK('NFL Teams'!M2,'NFL Teams'!$M$2:$M$33,0)) -> 12 | N2: =IF('NFL Teams'!N2="","",RANK('NFL Teams'!N2,'NFL Teams'!$N$2:$N$33,0)) -> 29 | O2: =IF('NFL Teams'!O2="","",RANK('NFL Teams'!O2,'NFL Teams'!$O$2:$O$33,0)) -> 30 | P2: =IF('NFL Teams'!P2="","",RANK('NFL Teams'!P2,'NFL Teams'!$P$2:$P$33,0)) -> 15
A3: ='NFL Teams'!A3 -> Atlanta Falcons | B3: =IF('NFL Teams'!B3="","",RANK('NFL Teams'!B3,'NFL Teams'!$B$2:$B$33,0)) -> 27 | C3: =IF('NFL Teams'!C3="","",RANK('NFL Teams'!C3,'NFL Teams'!$C$2:$C$33,0)) -> 14 | D3: =IF('NFL Teams'!D3="","",RANK('NFL Teams'!D3,'NFL Teams'!$D$2:$D$33,0)) -> 22 | E3: =IF('NFL Teams'!E3="","",RANK('NFL Teams'!E3,'NFL Teams'!$E$2:$E$33,0)) -> 28 | F3: =IF('NFL Teams'!F3="","",RANK('NFL Teams'!F3,'NFL Teams'!$F$2:$F$33,0)) -> 25 | G3: =IF('NFL Teams'!G3="","",RANK('NFL Teams'!G3,'NFL Teams'!$G$2:$G$33,0)) -> 28 | H3: =IF('NFL Teams'!H3="","",RANK('NFL Teams'!H3,'NFL Teams'!$H$2:$H$33,1)) -> 17 | I3: =IF('NFL Teams'!I3="","",RANK('NFL Teams'!I3,'NFL Teams'!$I$2:$I$33,0)) -> 11 | J3: =IF('NFL Teams'!J3="","",RANK('NFL Teams'!J3,'NFL Teams'!$J$2:$J$33,0)) -> 7 | K3: =IF('NFL Teams'!K3="","",RANK('NFL Teams'!K3,'NFL Teams'!$K$2:$K$33,0)) -> 25 | L3: =IF('NFL Teams'!L3="","",RANK('NFL Teams'!L3,'NFL Teams'!$L$2:$L$33,0)) -> 18 | M3: =IF('NFL Teams'!M3="","",RANK('NFL Teams'!M3,'NFL Teams'!$M$2:$M$33,0)) -> 8 | N3: =IF('NFL Teams'!N3="","",RANK('NFL Teams'!N3,'NFL Teams'!$N$2:$N$33,0)) -> 19 | O3: =IF('NFL Teams'!O3="","",RANK('NFL Teams'!O3,'NFL Teams'!$O$2:$O$33,0)) -> 22 | P3: =IF('NFL Teams'!P3="","",RANK('NFL Teams'!P3,'NFL Teams'!$P$2:$P$33,0)) -> 3
A4: ='NFL Teams'!A4 -> Baltimore Ravens | B4: =IF('NFL Teams'!B4="","",RANK('NFL Teams'!B4,'NFL Teams'!$B$2:$B$33,0)) -> 29 | C4: =IF('NFL Teams'!C4="","",RANK('NFL Teams'!C4,'NFL Teams'!$C$2:$C$33,0)) -> 32 | D4: =IF('NFL Teams'!D4="","",RANK('NFL Teams'!D4,'NFL Teams'!$D$2:$D$33,0)) -> 27 | E4: =IF('NFL Teams'!E4="","",RANK('NFL Teams'!E4,'NFL Teams'!$E$2:$E$33,0)) -> 3 | F4: =IF('NFL Teams'!F4="","",RANK('NFL Teams'!F4,'NFL Teams'!$F$2:$F$33,0)) -> 18 | G4: =IF('NFL Teams'!G4="","",RANK('NFL Teams'!G4,'NFL Teams'!$G$2:$G$33,0)) -> 27 | H4: =IF('NFL Teams'!H4="","",RANK('NFL Teams'!H4,'NFL Teams'!$H$2:$H$33,1)) -> 27 | I4: =IF('NFL Teams'!I4="","",RANK('NFL Teams'!I4,'NFL Teams'!$I$2:$I$33,0)) -> 10 | J4: =IF('NFL Teams'!J4="","",RANK('NFL Teams'!J4,'NFL Teams'!$J$2:$J$33,0)) -> 26 | K4: =IF('NFL Teams'!K4="","",RANK('NFL Teams'!K4,'NFL Teams'!$K$2:$K$33,0)) -> 15 | L4: =IF('NFL Teams'!L4="","",RANK('NFL Teams'!L4,'NFL Teams'!$L$2:$L$33,0)) -> 28 | M4: =IF('NFL Teams'!M4="","",RANK('NFL Teams'!M4,'NFL Teams'!$M$2:$M$33,0)) -> 21 | N4: =IF('NFL Teams'!N4="","",RANK('NFL Teams'!N4,'NFL Teams'!$N$2:$N$33,0)) -> 12 | O4: =IF('NFL Teams'!O4="","",RANK('NFL Teams'!O4,'NFL Teams'!$O$2:$O$33,0)) -> 11 | P4: =IF('NFL Teams'!P4="","",RANK('NFL Teams'!P4,'NFL Teams'!$P$2:$P$33,0)) -> 22
A5: ='NFL Teams'!A5 -> Buffalo Bills | B5: =IF('NFL Teams'!B5="","",RANK('NFL Teams'!B5,'NFL Teams'!$B$2:$B$33,0)) -> 21 | C5: =IF('NFL Teams'!C5="","",RANK('NFL Teams'!C5,'NFL Teams'!$C$2:$C$33,0)) -> 16 | D5: =IF('NFL Teams'!D5="","",RANK('NFL Teams'!D5,'NFL Teams'!$D$2:$D$33,0)) -> 18 | E5: =IF('NFL Teams'!E5="","",RANK('NFL Teams'!E5,'NFL Teams'!$E$2:$E$33,0)) -> 21 | F5: =IF('NFL Teams'!F5="","",RANK('NFL Teams'!F5,'NFL Teams'!$F$2:$F$33,0)) -> 14 | G5: =IF('NFL Teams'!G5="","",RANK('NFL Teams'!G5,'NFL Teams'!$G$2:$G$33,0)) -> 19 | H5: =IF('NFL Teams'!H5="","",RANK('NFL Teams'!H5,'NFL Teams'!$H$2:$H$33,1)) -> 10 | I5: =IF('NFL Teams'!I5="","",RANK('NFL Teams'!I5,'NFL Teams'!$I$2:$I$33,0)) -> 32 | J5: =IF('NFL Teams'!J5="","",RANK('NFL Teams'!J5,'NFL Teams'!$J$2:$J$33,0)) -> 3 | K5: =IF('NFL Teams'!K5="","",RANK('NFL Teams'!K5,'NFL Teams'!$K$2:$K$33,0)) -> 4 | L5: =IF('NFL Teams'!L5="","",RANK('NFL Teams'!L5,'NFL Teams'!$L$2:$L$33,0)) -> 26 | M5: =IF('NFL Teams'!M5="","",RANK('NFL Teams'!M5,'NFL Teams'!$M$2:$M$33,0)) -> 30 | N5: =IF('NFL Teams'!N5="","",RANK('NFL Teams'!N5,'NFL Teams'!$N$2:$N$33,0)) -> 11 | O5: =IF('NFL Teams'!O5="","",RANK('NFL Teams'!O5,'NFL Teams'!$O$2:$O$33,0)) -> 19 | P5: =IF('NFL Teams'!P5="","",RANK('NFL Teams'!P5,'NFL Teams'!$P$2:$P$33,0)) -> 27
A6: ='NFL Teams'!A6 -> Carolina Panthers | B6: =IF('NFL Teams'!B6="","",RANK('NFL Teams'!B6,'NFL Teams'!$B$2:$B$33,0)) -> 30 | C6: =IF('NFL Teams'!C6="","",RANK('NFL Teams'!C6,'NFL Teams'!$C$2:$C$33,0)) -> 30 | D6: =IF('NFL Teams'!D6="","",RANK('NFL Teams'!D6,'NFL Teams'!$D$2:$D$33,0)) -> 27 | E6: =IF('NFL Teams'!E6="","",RANK('NFL Teams'!E6,'NFL Teams'!$E$2:$E$33,0)) -> 26 | F6: =IF('NFL Teams'!F6="","",RANK('NFL Teams'!F6,'NFL Teams'!$F$2:$F$33,0)) -> 28 | G6: =IF('NFL Teams'!G6="","",RANK('NFL Teams'!G6,'NFL Teams'!$G$2:$G$33,0)) -> 28 | H6: =IF('NFL Teams'!H6="","",RANK('NFL Teams'!H6,'NFL Teams'!$H$2:$H$33,1)) -> 25 | I6: =IF('NFL Teams'!I6="","",RANK('NFL Teams'!I6,'NFL Teams'!$I$2:$I$33,0)) -> 6 | J6: =IF('NFL Teams'!J6="","",RANK('NFL Teams'!J6,'NFL Teams'!$J$2:$J$33,0)) -> 25 | K6: =IF('NFL Teams'!K6="","",RANK('NFL Teams'!K6,'NFL Teams'!$K$2:$K$33,0)) -> 22 | L6: =IF('NFL Teams'!L6="","",RANK('NFL Teams'!L6,'NFL Teams'!$L$2:$L$33,0)) -> 23 | M6: =IF('NFL Teams'!M6="","",RANK('NFL Teams'!M6,'NFL Teams'!$M$2:$M$33,0)) -> 20 | N6: =IF('NFL Teams'!N6="","",RANK('NFL Teams'!N6,'NFL Teams'!$N$2:$N$33,0)) -> 9 | O6: =IF('NFL Teams'!O6="","",RANK('NFL Teams'!O6,'NFL Teams'!$O$2:$O$33,0)) -> 24 | P6: =IF('NFL Teams'!P6="","",RANK('NFL Teams'!P6,'NFL Teams'!$P$2:$P$33,0)) -> 19
A7: ='NFL Teams'!A7 -> Chicago Bears | B7: =IF('NFL Teams'!B7="","",RANK('NFL Teams'!B7,'NFL Teams'!$B$2:$B$33,0)) -> 2 | C7: =IF('NFL Teams'!C7="","",RANK('NFL Teams'!C7,'NFL Teams'!$C$2:$C$33,0)) -> 5 | D7: =IF('NFL Teams'!D7="","",RANK('NFL Teams'!D7,'NFL Teams'!$D$2:$D$33,0)) -> 1 | E7: =IF('NFL Teams'!E7="","",RANK('NFL Teams'!E7,'NFL Teams'!$E$2:$E$33,0)) -> 5 | F7: =IF('NFL Teams'!F7="","",RANK('NFL Teams'!F7,'NFL Teams'!$F$2:$F$33,0)) -> 18 | G7: =IF('NFL Teams'!G7="","",RANK('NFL Teams'!G7,'NFL Teams'!$G$2:$G$33,0)) -> 1 | H7: =IF('NFL Teams'!H7="","",RANK('NFL Teams'!H7,'NFL Teams'!$H$2:$H$33,1)) -> 1 | I7: =IF('NFL Teams'!I7="","",RANK('NFL Teams'!I7,'NFL Teams'!$I$2:$I$33,0)) -> 31 | J7: =IF('NFL Teams'!J7="","",RANK('NFL Teams'!J7,'NFL Teams'!$J$2:$J$33,0)) -> 12 | K7: =IF('NFL Teams'!K7="","",RANK('NFL Teams'!K7,'NFL Teams'!$K$2:$K$33,0)) -> 7 | L7: =IF('NFL Teams'!L7="","",RANK('NFL Teams'!L7,'NFL Teams'!$L$2:$L$33,0)) -> 14 | M7: =IF('NFL Teams'!M7="","",RANK('NFL Teams'!M7,'NFL Teams'!$M$2:$M$33,0)) -> 5 | N7: =IF('NFL Teams'!N7="","",RANK('NFL Teams'!N7,'NFL Teams'!$N$2:$N$33,0)) -> 14 | O7: =IF('NFL Teams'!O7="","",RANK('NFL Teams'!O7,'NFL Teams'!$O$2:$O$33,0)) -> 16 | P7: =IF('NFL Teams'!P7="","",RANK('NFL Teams'!P7,'NFL Teams'!$P$2:$P$33,0)) -> 24
A8: ='NFL Teams'!A8 -> Cincinnati Bengals | B8: =IF('NFL Teams'!B8="","",RANK('NFL Teams'!B8,'NFL Teams'!$B$2:$B$33,0)) -> 26 | C8: =IF('NFL Teams'!C8="","",RANK('NFL Teams'!C8,'NFL Teams'!$C$2:$C$33,0)) -> 20 | D8: =IF('NFL Teams'!D8="","",RANK('NFL Teams'!D8,'NFL Teams'!$D$2:$D$33,0)) -> 24 | E8: =IF('NFL Teams'!E8="","",RANK('NFL Teams'!E8,'NFL Teams'!$E$2:$E$33,0)) -> 25 | F8: =IF('NFL Teams'!F8="","",RANK('NFL Teams'!F8,'NFL Teams'!$F$2:$F$33,0)) -> 25 | G8: =IF('NFL Teams'!G8="","",RANK('NFL Teams'!G8,'NFL Teams'!$G$2:$G$33,0)) -> 28 | H8: =IF('NFL Teams'!H8="","",RANK('NFL Teams'!H8,'NFL Teams'!$H$2:$H$33,1)) -> 20 | I8: =IF('NFL Teams'!I8="","",RANK('NFL Teams'!I8,'NFL Teams'!$I$2:$I$33,0)) -> 26 | J8: =IF('NFL Teams'!J8="","",RANK('NFL Teams'!J8,'NFL Teams'!$J$2:$J$33,0)) -> 15 | K8: =IF('NFL Teams'!K8="","",RANK('NFL Teams'!K8,'NFL Teams'!$K$2:$K$33,0)) -> 16 | L8: =IF('NFL Teams'!L8="","",RANK('NFL Teams'!L8,'NFL Teams'!$L$2:$L$33,0)) -> 17 | M8: =IF('NFL Teams'!M8="","",RANK('NFL Teams'!M8,'NFL Teams'!$M$2:$M$33,0)) -> 24 | N8: =IF('NFL Teams'!N8="","",RANK('NFL Teams'!N8,'NFL Teams'!$N$2:$N$33,0)) -> 20 | O8: =IF('NFL Teams'!O8="","",RANK('NFL Teams'!O8,'NFL Teams'!$O$2:$O$33,0)) -> 26 | P8: =IF('NFL Teams'!P8="","",RANK('NFL Teams'!P8,'NFL Teams'!$P$2:$P$33,0)) -> 26
A9: ='NFL Teams'!A9 -> Cleveland Browns | B9: =IF('NFL Teams'!B9="","",RANK('NFL Teams'!B9,'NFL Teams'!$B$2:$B$33,0)) -> 13 | C9: =IF('NFL Teams'!C9="","",RANK('NFL Teams'!C9,'NFL Teams'!$C$2:$C$33,0)) -> 11 | D9: =IF('NFL Teams'!D9="","",RANK('NFL Teams'!D9,'NFL Teams'!$D$2:$D$33,0)) -> 11 | E9: =IF('NFL Teams'!E9="","",RANK('NFL Teams'!E9,'NFL Teams'!$E$2:$E$33,0)) -> 17 | F9: =IF('NFL Teams'!F9="","",RANK('NFL Teams'!F9,'NFL Teams'!$F$2:$F$33,0)) -> 20 | G9: =IF('NFL Teams'!G9="","",RANK('NFL Teams'!G9,'NFL Teams'!$G$2:$G$33,0)) -> 8 | H9: =IF('NFL Teams'!H9="","",RANK('NFL Teams'!H9,'NFL Teams'!$H$2:$H$33,1)) -> 8 | I9: =IF('NFL Teams'!I9="","",RANK('NFL Teams'!I9,'NFL Teams'!$I$2:$I$33,0)) -> 20 | J9: =IF('NFL Teams'!J9="","",RANK('NFL Teams'!J9,'NFL Teams'!$J$2:$J$33,0)) -> 21 | K9: =IF('NFL Teams'!K9="","",RANK('NFL Teams'!K9,'NFL Teams'!$K$2:$K$33,0)) -> 8 | L9: =IF('NFL Teams'!L9="","",RANK('NFL Teams'!L9,'NFL Teams'!$L$2:$L$33,0)) -> 21 | M9: =IF('NFL Teams'!M9="","",RANK('NFL Teams'!M9,'NFL Teams'!$M$2:$M$33,0)) -> 28 | N9: =IF('NFL Teams'!N9="","",RANK('NFL Teams'!N9,'NFL Teams'!$N$2:$N$33,0)) -> 22 | O9: =IF('NFL Teams'!O9="","",RANK('NFL Teams'!O9,'NFL Teams'!$O$2:$O$33,0)) -> 10 | P9: =IF('NFL Teams'!P9="","",RANK('NFL Teams'!P9,'NFL Teams'!$P$2:$P$33,0)) -> 16
A10: ='NFL Teams'!A10 -> Dallas Cowboys | B10: =IF('NFL Teams'!B10="","",RANK('NFL Teams'!B10,'NFL Teams'!$B$2:$B$33,0)) -> 11 | C10: =IF('NFL Teams'!C10="","",RANK('NFL Teams'!C10,'NFL Teams'!$C$2:$C$33,0)) -> 26 | D10: =IF('NFL Teams'!D10="","",RANK('NFL Teams'!D10,'NFL Teams'!$D$2:$D$33,0)) -> 21 | E10: =IF('NFL Teams'!E10="","",RANK('NFL Teams'!E10,'NFL Teams'!$E$2:$E$33,0)) -> 1 | F10: =IF('NFL Teams'!F10="","",RANK('NFL Teams'!F10,'NFL Teams'!$F$2:$F$33,0)) -> 4 | G10: =IF('NFL Teams'!G10="","",RANK('NFL Teams'!G10,'NFL Teams'!$G$2:$G$33,0)) -> 4 | H10: =IF('NFL Teams'!H10="","",RANK('NFL Teams'!H10,'NFL Teams'!$H$2:$H$33,1)) -> 10 | I10: =IF('NFL Teams'!I10="","",RANK('NFL Teams'!I10,'NFL Teams'!$I$2:$I$33,0)) -> 4 | J10: =IF('NFL Teams'!J10="","",RANK('NFL Teams'!J10,'NFL Teams'!$J$2:$J$33,0)) -> 8 | K10: =IF('NFL Teams'!K10="","",RANK('NFL Teams'!K10,'NFL Teams'!$K$2:$K$33,0)) -> 27 | L10: =IF('NFL Teams'!L10="","",RANK('NFL Teams'!L10,'NFL Teams'!$L$2:$L$33,0)) -> 8 | M10: =IF('NFL Teams'!M10="","",RANK('NFL Teams'!M10,'NFL Teams'!$M$2:$M$33,0)) -> 6 | N10: =IF('NFL Teams'!N10="","",RANK('NFL Teams'!N10,'NFL Teams'!$N$2:$N$33,0)) -> 2 | O10: =IF('NFL Teams'!O10="","",RANK('NFL Teams'!O10,'NFL Teams'!$O$2:$O$33,0)) -> 3 | P10: =IF('NFL Teams'!P10="","",RANK('NFL Teams'!P10,'NFL Teams'!$P$2:$P$33,0)) -> 1
A11: ='NFL Teams'!A11 -> Denver Broncos | B11: =IF('NFL Teams'!B11="","",RANK('NFL Teams'!B11,'NFL Teams'!$B$2:$B$33,0)) -> 17 | C11: =IF('NFL Teams'!C11="","",RANK('NFL Teams'!C11,'NFL Teams'!$C$2:$C$33,0)) -> 21 | D11: =IF('NFL Teams'!D11="","",RANK('NFL Teams'!D11,'NFL Teams'!$D$2:$D$33,0)) -> 16 | E11: =IF('NFL Teams'!E11="","",RANK('NFL Teams'!E11,'NFL Teams'!$E$2:$E$33,0)) -> 11 | F11: =IF('NFL Teams'!F11="","",RANK('NFL Teams'!F11,'NFL Teams'!$F$2:$F$33,0)) -> 12 | G11: =IF('NFL Teams'!G11="","",RANK('NFL Teams'!G11,'NFL Teams'!$G$2:$G$33,0)) -> 19 | H11: =IF('NFL Teams'!H11="","",RANK('NFL Teams'!H11,'NFL Teams'!$H$2:$H$33,1)) -> 10 | I11: =IF('NFL Teams'!I11="","",RANK('NFL Teams'!I11,'NFL Teams'!$I$2:$I$33,0)) -> 5 | J11: =IF('NFL Teams'!J11="","",RANK('NFL Teams'!J11,'NFL Teams'!$J$2:$J$33,0)) -> 17 | K11: =IF('NFL Teams'!K11="","",RANK('NFL Teams'!K11,'NFL Teams'!$K$2:$K$33,0)) -> 14 | L11: =IF('NFL Teams'!L11="","",RANK('NFL Teams'!L11,'NFL Teams'!$L$2:$L$33,0)) -> 7 | M11: =IF('NFL Teams'!M11="","",RANK('NFL Teams'!M11,'NFL Teams'!$M$2:$M$33,0)) -> 19 | N11: =IF('NFL Teams'!N11="","",RANK('NFL Teams'!N11,'NFL Teams'!$N$2:$N$33,0)) -> 15 | O11: =IF('NFL Teams'!O11="","",RANK('NFL Teams'!O11,'NFL Teams'!$O$2:$O$33,0)) -> 20 | P11: =IF('NFL Teams'!P11="","",RANK('NFL Teams'!P11,'NFL Teams'!$P$2:$P$33,0)) -> 17
A12: ='NFL Teams'!A12 -> Detroit Lions | B12: =IF('NFL Teams'!B12="","",RANK('NFL Teams'!B12,'NFL Teams'!$B$2:$B$33,0)) -> 9 | C12: =IF('NFL Teams'!C12="","",RANK('NFL Teams'!C12,'NFL Teams'!$C$2:$C$33,0)) -> 2 | D12: =IF('NFL Teams'!D12="","",RANK('NFL Teams'!D12,'NFL Teams'!$D$2:$D$33,0)) -> 4 | E12: =IF('NFL Teams'!E12="","",RANK('NFL Teams'!E12,'NFL Teams'!$E$2:$E$33,0)) -> 23 | F12: =IF('NFL Teams'!F12="","",RANK('NFL Teams'!F12,'NFL Teams'!$F$2:$F$33,0)) -> 28 | G12: =IF('NFL Teams'!G12="","",RANK('NFL Teams'!G12,'NFL Teams'!$G$2:$G$33,0)) -> 8 | H12: =IF('NFL Teams'!H12="","",RANK('NFL Teams'!H12,'NFL Teams'!$H$2:$H$33,1)) -> 6 | I12: =IF('NFL Teams'!I12="","",RANK('NFL Teams'!I12,'NFL Teams'!$I$2:$I$33,0)) -> 28 | J12: =IF('NFL Teams'!J12="","",RANK('NFL Teams'!J12,'NFL Teams'!$J$2:$J$33,0)) -> 16 | K12: =IF('NFL Teams'!K12="","",RANK('NFL Teams'!K12,'NFL Teams'!$K$2:$K$33,0)) -> 5 | L12: =IF('NFL Teams'!L12="","",RANK('NFL Teams'!L12,'NFL Teams'!$L$2:$L$33,0)) -> 19 | M12: =IF('NFL Teams'!M12="","",RANK('NFL Teams'!M12,'NFL Teams'!$M$2:$M$33,0)) -> 15 | N12: =IF('NFL Teams'!N12="","",RANK('NFL Teams'!N12,'NFL Teams'!$N$2:$N$33,0)) -> 16 | O12: =IF('NFL Teams'!O12="","",RANK('NFL Teams'!O12,'NFL Teams'!$O$2:$O$33,0)) -> 14 | P12: =IF('NFL Teams'!P12="","",RANK('NFL Teams'!P12,'NFL Teams'!$P$2:$P$33,0)) -> 29
A13: ='NFL Teams'!A13 -> Green Bay Packers | B13: =IF('NFL Teams'!B13="","",RANK('NFL Teams'!B13,'NFL Teams'!$B$2:$B$33,0)) -> 1 | C13: =IF('NFL Teams'!C13="","",RANK('NFL Teams'!C13,'NFL Teams'!$C$2:$C$33,0)) -> 7 | D13: =IF('NFL Teams'!D13="","",RANK('NFL Teams'!D13,'NFL Teams'!$D$2:$D$33,0)) -> 3 | E13: =IF('NFL Teams'!E13="","",RANK('NFL Teams'!E13,'NFL Teams'!$E$2:$E$33,0)) -> 1 | F13: =IF('NFL Teams'!F13="","",RANK('NFL Teams'!F13,'NFL Teams'!$F$2:$F$33,0)) -> 3 | G13: =IF('NFL Teams'!G13="","",RANK('NFL Teams'!G13,'NFL Teams'!$G$2:$G$33,0)) -> 2 | H13: =IF('NFL Teams'!H13="","",RANK('NFL Teams'!H13,'NFL Teams'!$H$2:$H$33,1)) -> 1 | I13: =IF('NFL Teams'!I13="","",RANK('NFL Teams'!I13,'NFL Teams'!$I$2:$I$33,0)) -> 3 | J13: =IF('NFL Teams'!J13="","",RANK('NFL Teams'!J13,'NFL Teams'!$J$2:$J$33,0)) -> 32 | K13: =IF('NFL Teams'!K13="","",RANK('NFL Teams'!K13,'NFL Teams'!$K$2:$K$33,0)) -> 3 | L13: =IF('NFL Teams'!L13="","",RANK('NFL Teams'!L13,'NFL Teams'!$L$2:$L$33,0)) -> 13 | M13: =IF('NFL Teams'!M13="","",RANK('NFL Teams'!M13,'NFL Teams'!$M$2:$M$33,0)) -> 32 | N13: =IF('NFL Teams'!N13="","",RANK('NFL Teams'!N13,'NFL Teams'!$N$2:$N$33,0)) -> 8 | O13: =IF('NFL Teams'!O13="","",RANK('NFL Teams'!O13,'NFL Teams'!$O$2:$O$33,0)) -> 21 | P13: =IF('NFL Teams'!P13="","",RANK('NFL Teams'!P13,'NFL Teams'!$P$2:$P$33,0)) -> 24
... A33: ='NFL Teams'!A33 -> Washington Commanders | B33: =IF('NFL Teams'!B33="","",RANK('NFL Teams'!B33,'NFL Teams'!$B$2:$B$33,0)) -> 6 | C33: =IF('NFL Teams'!C33="","",RANK('NFL Teams'!C33,'NFL Teams'!$C$2:$C$33,0)) -> 4 | D33: =IF('NFL Teams'!D33="","",RANK('NFL Teams'!D33,'NFL Teams'!$D$2:$D$33,0)) -> 6 | E33: =IF('NFL Teams'!E33="","",RANK('NFL Teams'!E33,'NFL Teams'!$E$2:$E$33,0)) -> 20 | F33: =IF('NFL Teams'!F33="","",RANK('NFL Teams'!F33,'NFL Teams'!$F$2:$F$33,0)) -> 9 | G33: =IF('NFL Teams'!G33="","",RANK('NFL Teams'!G33,'NFL Teams'!$G$2:$G$33,0)) -> 7 | H33: =IF('NFL Teams'!H33="","",RANK('NFL Teams'!H33,'NFL Teams'!$H$2:$H$33,1)) -> 7 | I33: =IF('NFL Teams'!I33="","",RANK('NFL Teams'!I33,'NFL Teams'!$I$2:$I$33,0)) -> 29 | J33: =IF('NFL Teams'!J33="","",RANK('NFL Teams'!J33,'NFL Teams'!$J$2:$J$33,0)) -> 24 | K33: =IF('NFL Teams'!K33="","",RANK('NFL Teams'!K33,'NFL Teams'!$K$2:$K$33,0)) -> 18 | L33: =IF('NFL Teams'!L33="","",RANK('NFL Teams'!L33,'NFL Teams'!$L$2:$L$33,0)) -> 27 | M33: =IF('NFL Teams'!M33="","",RANK('NFL Teams'!M33,'NFL Teams'!$M$2:$M$33,0)) -> 9 | N33: =IF('NFL Teams'!N33="","",RANK('NFL Teams'!N33,'NFL Teams'!$N$2:$N$33,0)) -> 26 | O33: =IF('NFL Teams'!O33="","",RANK('NFL Teams'!O33,'NFL Teams'!$O$2:$O$33,0)) -> 15 | P33: =IF('NFL Teams'!P33="","",RANK('NFL Teams'!P33,'NFL Teams'!$P$2:$P$33,0)) -> 14
A35: Rang 1 = bester Wert in Spielrichtung (siehe Blatt Kategorien). Gleiche Werte = gleicher Rang. Formeln beziehen sich live auf das Datenblatt.

Sheet Kategorien
A1: # | B1: Kategorie | C1: Einheit | D1: Rang 1 = | E1: Datenqualität | F1: Mindestabstand im Spiel | G1: Zu nahe Paare | H1: Definition / Hinweis | I1: Quelle
A2: 1 | B2: Siege (Regular Season, all-time) | C2: Siege | D2: meiste | E2: hart | F2: ≥ 20 Siege | G2: =COUNTIF('Paar-Check'!$A:$A,B2) -> 35 | H2: Alle Regular-Season-Siege inkl. AFL/AAFC, Stand Ende Saison 2025. | I2: Wikipedia 'Lists of NFL team seasons' (Quelle PFR)
A3: 2 | B3: Niederlagen (Regular Season, all-time) | C3: Niederlagen | D3: meiste | E3: hart | F3: ≥ 20 Niederlagen | G3: =COUNTIF('Paar-Check'!$A:$A,B3) -> 42 | H3: Alle Regular-Season-Niederlagen, Stand Ende Saison 2025. | I3: Wikipedia 'Lists of NFL team seasons' (Quelle PFR)
A4: 3 | B4: Unentschieden (all-time) | C4: Remis | D4: meiste | E4: hart | F4: ≥ 2 Remis | G4: =COUNTIF('Paar-Check'!$A:$A,B4) -> 47 | H4: Alle Remis in der Regular Season seit Gründung. | I4: Wikipedia 'Lists of NFL team seasons' (Quelle PFR)
A5: 4 | B5: Siegquote (Regular Season, all-time) | C5: % | D5: höchste | E5: hart | F5: ≥ 1 Prozentpunkt | G5: =COUNTIF('Paar-Check'!$A:$A,B5) -> 56 | H5: Siege / Spiele, Remis als halber Sieg. | I5: Wikipedia 'Lists of NFL team seasons' (Quelle PFR)
A6: 5 | B6: Playoff-Siege (all-time) | C6: Siege | D6: meiste | E6: hart | F6: ≥ 2 Siege | G6: =COUNTIF('Paar-Check'!$A:$A,B6) -> 45 | H6: Alle Playoff-Siege inkl. Super Bowl, Stand nach Super Bowl LX (Feb. 2026). | I6: Wikipedia 'Lists of NFL team seasons' + Playoffs 2025/26
A7: 6 | B7: Hall-of-Famers | C7: Personen | D7: meiste | E7: mittel | F7: ≥ 2 Personen | G7: =COUNTIF('Paar-Check'!$A:$A,B7) -> 50 | H7: Mitglieder der Pro Football Hall of Fame, je Person ein Primärteam, inkl. Class of 2026. | I7: LegionReport 'NFL Hall of Famers by Team' (Juli 2026)
A8: 7 | B8: In der heutigen Stadt seit | C8: Jahr | D8: am längsten | E8: hart | F8: ≥ 3 Jahre | G8: =COUNTIF('Paar-Check'!$A:$A,B8) -> 35 | H8: Erste Saison am heutigen Standort (Umzüge zählen neu). | I8: Franchise-Geschichten (Wikipedia/NFL)
A9: 8 | B9: Stadionkapazität | C9: Plätze | D9: grösste | E9: hart | F9: ≥ 1500 Plätze | G9: =COUNTIF('Paar-Check'!$A:$A,B9) -> 78 | H9: Reguläre Sitzplätze Heimstadion Saison 2026. | I9: Wikipedia 'List of current NFL stadiums'
A10: 9 | B10: Stadion-Baukosten | C10: Mio. USD | D10: höchste | E10: mittel | F10: ≥ 15 % Unterschied | G10: =COUNTIF('Paar-Check'!$A:$A,B10) -> 37 | H10: Nominale Baukosten des heutigen Stadions im Baujahr (nicht inflationsbereinigt). Soldier Field = Umbau 2003. | I10: Sports-King 'Complete History of Every NFL Stadium' (2026)
A11: 10 | B11: Breitengrad Stadion | C11: ° Nord | D11: nördlichstes | E11: hart | F11: ≥ 0.75 °Nord | G11: =COUNTIF('Paar-Check'!$A:$A,B11) -> 42 | H11: Geografische Breite des Heimstadions (gerundet). | I11: Stadion-Koordinaten (Wikipedia), gerundet
A12: 11 | B12: Längengrad Stadion | C12: ° West | D12: westlichstes | E12: hart | F12: ≥ 1 °West | G12: =COUNTIF('Paar-Check'!$A:$A,B12) -> 18 | H12: Geografische Länge des Heimstadions (West = positiv). | I12: Stadion-Koordinaten (Wikipedia), gerundet
A13: 12 | B13: Einwohner Metropolregion | C13: Mio. | D13: grösste | E13: hart | F13: ≥ 10 % Unterschied | G13: =COUNTIF('Paar-Check'!$A:$A,B13) -> 38 | H13: Metropolitan Statistical Area des Teammarkts, Schätzung 1.7.2025. | I13: US Census Bureau Vintage 2025 via Wikipedia 'List of core-based statistical areas'
... A16: 15 | B16: Betriebsgewinn Saison 2025 | C16: Mio. USD | D16: höchster | E16: mittel | F16: ≥ 10 % Unterschied | G16: =COUNTIF('Paar-Check'!$A:$A,B16) -> 44 | H16: Forbes-Schätzung Operating Income (EBITDA) 2025. | I16: Forbes 'The NFL's Most Valuable Teams 2026' (09.09.2026)
A19: Hinweise
A20: Stand 23.09.2026. Erfolgsdaten nach Saison 2025 (Super Bowl LX), Stadien Saison 2026, Einwohner Census 2025, Forbes 09.09.2026, Social Media Feb. 2026.
A21: Auswahlkriterium: Werte breit gestreut, möglichst ohne Gleichstände. Nicht mehr enthalten, weil zu viele gleiche oder fast gleiche Werte: Super-Bowl-Siege/-Teilnahmen, #1-Picks, gesperrte Nummern, Divisionstitel, Franchise-Wert, Umsatz, Gründungsjahr.
A22: Mindestabstand: Das Spiel soll zwei Teams nur dann in dieselbe Runde losen, wenn sich ihre Werte mindestens um diesen Abstand unterscheiden. Alle Verstösse stehen im Blatt 'Paar-Check'.
A23: Unvermeidbare Gleichstände: Giants/Jets und Rams/Chargers teilen sich Stadion und Metropolregion – diese Paare nie gemeinsam in einer Stadion-/Geo-/Einwohner-Runde verwenden.

Sheet Paar-Check
A1: Kategorie | B1: Team A | C1: Wert A | D1: Team B | E1: Wert B | F1: Differenz
A2: Siege (Regular Season, all-time) | B2: Arizona Cardinals | C2: 596 | D2: Detroit Lions | E2: 615 | F2: 19
A3: Siege (Regular Season, all-time) | B3: Atlanta Falcons | C3: 406 | D3: Cincinnati Bengals | E3: 409 | F3: 3
A4: Siege (Regular Season, all-time) | B4: Atlanta Falcons | C4: 406 | D4: New Orleans Saints | E4: 423 | F4: 17
A5: Siege (Regular Season, all-time) | B5: Atlanta Falcons | C5: 406 | D5: Seattle Seahawks | E5: 416 | F5: 10
A6: Siege (Regular Season, all-time) | B6: Buffalo Bills | C6: 498 | D6: Las Vegas Raiders | E6: 512 | F6: 14
A7: Siege (Regular Season, all-time) | B7: Buffalo Bills | C7: 498 | D7: Los Angeles Chargers | E7: 505 | F7: 7
A8: Siege (Regular Season, all-time) | B8: Buffalo Bills | C8: 498 | D8: Miami Dolphins | E8: 511 | F8: 13
A9: Siege (Regular Season, all-time) | B9: Buffalo Bills | C9: 498 | D9: Tennessee Titans | E9: 482 | F9: 16
A10: Siege (Regular Season, all-time) | B10: Carolina Panthers | C10: 227 | D10: Jacksonville Jaguars | E10: 215 | F10: 12
A11: Siege (Regular Season, all-time) | B11: Chicago Bears | C11: 809 | D11: Green Bay Packers | E11: 819 | F11: 10
A12: Siege (Regular Season, all-time) | B12: Cincinnati Bengals | C12: 409 | D12: New Orleans Saints | E12: 423 | F12: 14
A13: Siege (Regular Season, all-time) | B13: Cincinnati Bengals | C13: 409 | D13: Seattle Seahawks | E13: 416 | F13: 7
... A688: Betriebsgewinn Saison 2025 | B688: Seattle Seahawks | C688: 131 | D688: Washington Commanders | E688: 121 | F688: 10
